planhat/__init__.py
planhat/client.py
planhat/errors.py
planhat/py.typed
planhat/session.py
planhat/types.py
robocorp_planhat-1.0.0.dist-info/LICENSE
robocorp_planhat-1.0.0.dist-info/METADATA
robocorp_planhat-1.0.0.dist-info/WHEEL
robocorp_planhat-1.0.0.dist-info/RECORD
